{
  "99999999": {
    "usesLeft": 0,
    "totalDevices": 1,
    "devices": [
      "web-95u29c7a82"
    ],
    "expireAt": 1777657240441,
    "createdAt": 1775065240441,
    "deviceStates": {
      "web-95u29c7a82": {
        "f1": false,
        "f2": false,
        "f3": false,
        "f4": false,
        "f5": false,
        "f6": false,
        "f7": false,
        "sensi": "60"
      }
    }
  },
  "ATH-KADH-DSOR": {
    "usesLeft": 1,
    "totalDevices": 1,
    "devices": [],
    "expireAt": 1777092069483,
    "createdAt": 1774500069483
  },
  "HFT-VIP2DEV-02": {
    "usesLeft": 0,
    "totalDevices": 1,
    "devices": [
      "web-6cutz43yc8"
    ],
    "expireAt": 10414414749883,
    "createdAt": 1774501149883
  },
  "ATH-0UX6-58XH": {
    "usesLeft": 0,
    "totalDevices": 1,
    "devices": [
      "web-uicxbnrxw0"
    ],
    "expireAt": 10414414914084,
    "createdAt": 1774501314084
  },
  "HFT-SD8FDSBF9J": {
    "usesLeft": 0,
    "totalDevices": 1,
    "devices": [
      "web-6p79gggwsn"
    ],
    "expireAt": 10414414967068,
    "createdAt": 1774501367068
  },
  "ATH-TCDO-P0FF": {
    "usesLeft": 0,
    "totalDevices": 1,
    "devices": [
      "web-2od99dspxs"
    ],
    "expireAt": 10414414986004,
    "createdAt": 1774501386004
  },
  "ATH-0UX6-58XKO": {
    "usesLeft": 0,
    "totalDevices": 2,
    "devices": [
      "web-g9wr29g5f8",
      "web-ie87vpts32"
    ],
    "expireAt": 10415547817863,
    "createdAt": 1775634217863
  },
  "ATH-1D0E-TF1F": {
    "usesLeft": 0,
    "totalDevices": 2,
    "devices": [
      "web-9qqy6c2of9",
      "web-opd24sargn"
    ],
    "expireAt": 10414846481046,
    "createdAt": 1774932881046
  },
  "ATH-T0S4-7JJP": {
    "usesLeft": 0,
    "totalDevices": 1,
    "devices": [
      "web-ks582s59o7"
    ],
    "expireAt": 10414420891781,
    "createdAt": 1774507291781
  },
  "HFT-VIP2DEV-01": {
    "usesLeft": 0,
    "totalDevices": 1,
    "devices": [
      "web-npzq8ibrhn"
    ],
    "expireAt": 2638423953076,
    "createdAt": 1774510353076
  },
  "ATH-OAGK-M368": {
    "usesLeft": 0,
    "totalDevices": 1,
    "devices": [
      "web-ac9d2timfb"
    ],
    "expireAt": 1777010025411,
    "createdAt": 1775886825411
  },
  "ATH-77WT-PFA6": {
    "usesLeft": 0,
    "totalDevices": 1,
    "devices": [
      "web-xag0dw3c1t"
    ],
    "expireAt": 88174435304905,
    "createdAt": 1774521704905
  },
  "ATH-8ST3-2D0X": {
    "usesLeft": 0,
    "totalDevices": 1,
    "devices": [
      "web-6al8scd0wi"
    ],
    "expireAt": 88174436492036,
    "createdAt": 1774522892036
  },
  "ATH-GFQ5-TT0E": {
    "usesLeft": 0,
    "totalDevices": 1,
    "devices": [
      "web-z7d90fu6bn"
    ],
    "expireAt": 10414440324105,
    "createdAt": 1774526724105
  },
  "ATH-57HU-HSR5": {
    "usesLeft": 0,
    "totalDevices": 1,
    "devices": [
      "web-uat5fs77q5"
    ],
    "expireAt": 88174442277214,
    "createdAt": 1774528677214
  },
  "ATH-JYTX-R5N0": {
    "usesLeft": 0,
    "totalDevices": 1,
    "devices": [
      "web-4w5m55tcmz"
    ],
    "expireAt": 10414448641678,
    "createdAt": 1774535041679
  },
  "ATH-D3EB-0X6R": {
    "usesLeft": 0,
    "totalDevices": 2,
    "devices": [
      "web-776pbs3zp8",
      "web-6hacuqzkuj"
    ],
    "expireAt": 10414713952814,
    "createdAt": 1774800352815
  },
  "ATH-PVMI-W1GG": {
    "usesLeft": 0,
    "totalDevices": 1,
    "devices": [
      "web-z8kd2ya3qd"
    ],
    "expireAt": 2638519966612,
    "createdAt": 1774606366617
  },
  "ATH-QKXQ-0DLQ": {
    "usesLeft": 0,
    "totalDevices": 1,
    "devices": [
      "web-d14g99vg7t"
    ],
    "expireAt": 10414521440832,
    "createdAt": 1774607840832
  },
  "ATH-V6K2-EI7P": {
    "usesLeft": 0,
    "totalDevices": 1,
    "devices": [
      "web-ynhixdoa0u"
    ],
    "expireAt": 1776348508302,
    "createdAt": 1774620508302
  },
  "ATH-3RXL-2DHG": {
    "usesLeft": 48,
    "totalDevices": 50,
    "devices": [
      "web-eglm7oegcr",
      "web-h8tl1h4g1n"
    ],
    "expireAt": 1777213718126,
    "createdAt": 1774621718126
  },
  "ATH-YSFL-00LQ": {
    "usesLeft": 0,
    "totalDevices": 1,
    "devices": [
      "web-s6cevxralx"
    ],
    "expireAt": 10414597592722,
    "createdAt": 1774683992722
  },
  "ATH-9GFK-46NE": {
    "usesLeft": 0,
    "totalDevices": 1,
    "devices": [
      "web-kt0jivg4d7"
    ],
    "expireAt": 865774603515282,
    "createdAt": 1774689915282
  },
  "ATH-5JFZ-JN07": {
    "usesLeft": 0,
    "totalDevices": 1,
    "devices": [
      "web-eglm7oegcr"
    ],
    "expireAt": 1777284588845,
    "createdAt": 1774692588845
  },
  "HFT-3DAYREAPP": {
    "usesLeft": 0,
    "totalDevices": 1,
    "devices": [
      "web-t6j39ikjau"
    ],
    "expireAt": 1777312250504,
    "createdAt": 1774720250504
  },
  "ATH-8Q2R-7QQO": {
    "usesLeft": 0,
    "totalDevices": 1,
    "devices": [
      "web-95geynfhy4"
    ],
    "expireAt": 10414662793565,
    "createdAt": 1774749193565
  },
  "ATH-RIX5-LUUP": {
    "usesLeft": 0,
    "totalDevices": 2,
    "devices": [
      "web-xxwxwb1pur",
      "web-95u29c7a82"
    ],
    "expireAt": 88174663764445,
    "createdAt": 1774750164445
  },
  "ATH-2WEQ-ROJG": {
    "usesLeft": 0,
    "totalDevices": 1,
    "devices": [
      "web-h8tl1h4g1n"
    ],
    "expireAt": 1777353680753,
    "createdAt": 1774761680753
  },
  "ATH-21GE-B7WB": {
    "usesLeft": 1,
    "totalDevices": 1,
    "devices": [],
    "expireAt": 10414676424032,
    "createdAt": 1774762824032
  },
  "HFT-K6AS": {
    "usesLeft": 0,
    "totalDevices": 2,
    "devices": [
      "web-ny4283kvjp",
      "web-95u29c7a82"
    ],
    "expireAt": 10414676949370,
    "createdAt": 1774763349370
  },
  "ATH-U6M7-RJIO": {
    "usesLeft": 1,
    "totalDevices": 2,
    "devices": [
      "web-tfzzm42b8b"
    ],
    "expireAt": 10414678124880,
    "createdAt": 1774764524880
  },
  "ATH-LL1S-PKJR": {
    "usesLeft": 0,
    "totalDevices": 2,
    "devices": [
      "web-l501x0wfm8",
      "web-95u29c7a82"
    ],
    "expireAt": 865774698720169,
    "createdAt": 1774785120169
  },
  "ATH-HDMC-HCOB": {
    "usesLeft": 0,
    "totalDevices": 2,
    "devices": [
      "web-0ae18gxple",
      "web-95u29c7a82"
    ],
    "expireAt": 10414706515767,
    "createdAt": 1774792915767
  },
  "ATH-PD6F-8PUP": {
    "usesLeft": 0,
    "totalDevices": 2,
    "devices": [
      "web-zrxf0j8lep",
      "web-6dtqc6gprh"
    ],
    "expireAt": 865774783850298,
    "createdAt": 1774870250298
  },
  "ATH-JQUO-7T3H": {
    "usesLeft": 1,
    "totalDevices": 2,
    "devices": [
      "web-8i5zzgqi80"
    ],
    "expireAt": 865774785411646,
    "createdAt": 1774871811646
  },
  "ATH-325H-CF8A": {
    "usesLeft": 0,
    "totalDevices": 2,
    "devices": [
      "web-w4bhbfabff",
      "web-70x7zelsrd"
    ],
    "expireAt": 88174787915011,
    "createdAt": 1774874315011
  },
  "ATH-5FIO-MPDX": {
    "usesLeft": 1,
    "totalDevices": 2,
    "devices": [
      "web-9vemyqcwto"
    ],
    "expireAt": 10414865554169,
    "createdAt": 1774951954169
  },
  "ATH-7HVQ-NHDL": {
    "usesLeft": 0,
    "totalDevices": 2,
    "devices": [
      "web-boehf2xnmp",
      "web-wpvx7ga6r6"
    ],
    "expireAt": 86401774972284700,
    "createdAt": 1775058684708
  },
  "ATH-S93X-ZKQR": {
    "usesLeft": 1,
    "totalDevices": 2,
    "devices": [
      "web-eglm7oegcr"
    ],
    "expireAt": 1777650691570,
    "createdAt": 1775058691570
  },
  "LYTOAN": {
    "usesLeft": 0,
    "totalDevices": 2,
    "devices": [
      "web-eglm7oegcr",
      "web-wpvx7ga6r6"
    ],
    "expireAt": 1777721310228,
    "createdAt": 1775129310228
  },
  "ATH-J8CL-910F": {
    "usesLeft": 1,
    "totalDevices": 2,
    "devices": [
      "web-6uf44kpe6f"
    ],
    "expireAt": 88175044315798,
    "createdAt": 1775130715798
  },
  "ATH-SLB2-PDUU": {
    "usesLeft": 0,
    "totalDevices": 2,
    "devices": [
      "web-0xw32kplsj",
      "web-95u29c7a82"
    ],
    "expireAt": 10415048745879,
    "createdAt": 1775135145879
  },
  "ATH-X1ES-Q4PE": {
    "usesLeft": 1,
    "totalDevices": 2,
    "devices": [
      "web-9s8a1wwa1t"
    ],
    "expireAt": 88175065343421,
    "createdAt": 1775151743422
  },
  "ATH-MPZ4-9BNF": {
    "usesLeft": 0,
    "totalDevices": 2,
    "devices": [
      "web-3nguy0s5sl",
      "web-95u29c7a82"
    ],
    "expireAt": 10415109666732,
    "createdAt": 1775196066732
  },
  "ATH-8BPE-5ZJZ": {
    "usesLeft": 0,
    "totalDevices": 2,
    "devices": [
      "web-9vyvc1xx87",
      "web-f26mw6j3we"
    ],
    "expireAt": 88175124917660,
    "createdAt": 1775211317661
  },
  "ATH-663C-MYR6": {
    "usesLeft": 1,
    "totalDevices": 2,
    "devices": [
      "web-ren9u0zt8t"
    ],
    "expireAt": 8641775137122581,
    "createdAt": 1775223522603
  },
  "ATH-ZUDB-EMN9": {
    "usesLeft": 0,
    "totalDevices": 2,
    "devices": [
      "web-dz9vw8ela6",
      "web-h8tl1h4g1n"
    ],
    "expireAt": 88175192176795,
    "createdAt": 1775278576795
  },
  "ATH-KIL8-HVF3": {
    "usesLeft": 0,
    "totalDevices": 2,
    "devices": [
      "web-c4gle6km8o",
      "web-uyn3no49e1"
    ],
    "expireAt": 10415216540223,
    "createdAt": 1775302940223
  },
  "ATH-YVH0-SZ2N": {
    "usesLeft": 1,
    "totalDevices": 2,
    "devices": [
      "web-0zalz32har"
    ],
    "expireAt": 86401775257992960,
    "createdAt": 1775344392963
  },
  "ATH-W2ZO-IYB4": {
    "usesLeft": 0,
    "totalDevices": 1,
    "devices": [
      "web-h8tl1h4g1n"
    ],
    "expireAt": 1778085589274,
    "createdAt": 1775493589274
  },
  "ATH-WPII-FXXL": {
    "usesLeft": 1,
    "totalDevices": 2,
    "devices": [
      "web-6yxwkm0fda"
    ],
    "expireAt": 865775479696953,
    "createdAt": 1775566096953
  },
  "huy22": {
    "devices": [
      "web-lpomp1cl5j",
      "web-9vyvc1xx87"
    ],
    "usesLeft": 0,
    "totalDevices": 2,
    "expireAt": 4102444800000,
    "createdAt": 1744089000000
  },
  "huykey": {
    "usesLeft": 0,
    "totalDevices": 5,
    "devices": [
      "web-72uiehb4sd",
      "web-zt32tbogrj",
      "web-95u29c7a82",
      "web-z9u70b0m1m",
      "web-rh15t5cbum"
    ],
    "expireAt": 10415628539540,
    "createdAt": 1775714939540
  },
  "ATH-9LOT-BZTQ": {
    "usesLeft": 0,
    "totalDevices": 1,
    "devices": [
      "web-i82cdzoter"
    ],
    "expireAt": 10415652071074,
    "createdAt": 1775738471074
  },
  "hh": {
    "usesLeft": 0,
    "totalDevices": 1,
    "devices": [
      "web-r88r5renni"
    ],
    "expireAt": 1778419004694,
    "createdAt": 1775827004694
  },
  "ATH-IG1P-MR4I": {
    "usesLeft": 0,
    "totalDevices": 1,
    "devices": [
      "web-h8tl1h4g1n"
    ],
    "expireAt": 1778433571540,
    "createdAt": 1775841571540
  },
  "huynek": {
    "usesLeft": 0,
    "totalDevices": 2,
    "devices": [
      "web-h8tl1h4g1n",
      "web-2t3mi4pk8u"
    ],
    "expireAt": 88175757207991,
    "createdAt": 1775843607991
  },
  "ATH-5U6R-TF93": {
    "usesLeft": 0,
    "totalDevices": 1,
    "devices": [
      "web-tjwoit9oia"
    ],
    "expireAt": 88175784453675,
    "createdAt": 1775870853675
  },
  "HUY-TGQQO88": {
    "usesLeft": 0,
    "totalDevices": 600,
    "devices": [
      "web-h8tl1h4g1n",
      "web-ir4xz433ym",
      "web-8ln075atc6",
      "web-8gr6j69akb",
      "web-wlf53procl",
      "web-v9irf28sym",
      "web-hrns4z9y11",
      "web-9h1a8do2gr",
      "web-o74m3rm9dg",
      "web-56mrwzycmv",
      "web-go7ogd0tuq",
      "web-3mp9cuwack",
      "web-m4bphaolwj",
      "web-8qr6ot75pj",
      "web-xxo8ol2nsb",
      "web-khdqxx6irl",
      "web-87cnpal7tc",
      "web-fh5w07dpar",
      "web-n46qkhcmkd",
      "web-xftl9b5hli",
      "web-vw9czh7ezp",
      "web-408p8sz9ch",
      "web-mcjvmmip41",
      "web-rx9rg8me13",
      "web-jtwafmkik2",
      "web-5pi7i19a5w",
      "web-8i610e3yef",
      "web-ln54wp0fal",
      "web-a4gd89ugn9",
      "web-giy6fj0tx4",
      "web-mtu3je3zav",
      "web-kwfm91iw0c",
      "web-64m8zsphl7",
      "web-llft96hw2z",
      "web-ovn6aj1bz5",
      "web-w40bm1otwy",
      "web-c3aqdguriy",
      "web-6j1fgu3xb3",
      "web-l32r0f8d9q",
      "web-zm46upkhdo",
      "web-7yi7no6m49",
      "web-a4hx1rt849",
      "web-5mn2do6xx3",
      "web-qkmgzyssk9",
      "web-y96blc0km8",
      "web-gn0lmez7t1",
      "web-zwn5phkfac",
      "web-8r2dx0m74a",
      "web-ystse5dm4f",
      "web-wzu7jg0jwp",
      "web-oetbkxqis9",
      "web-u1qtkjnf5g",
      "web-9t32fyop1t",
      "web-0anuejbh8c",
      "web-vdapqaruap",
      "web-o0e9g0jqs6",
      "web-2lghsfdk61",
      "web-h5g6i7zl",
      "web-5vcp8nheyh",
      "web-o9gw74jpve",
      "web-u4896j9bon",
      "web-9senl2hsmz",
      "web-4t92l6wq8t",
      "web-3o73aojr9u",
      "web-alupucwksg",
      "web-c7yiz6gxls",
      "web-nljjae93ze",
      "web-wazf08mc3n",
      "web-gxox7iaelq",
      "web-1zbwn65yer",
      "web-ow31hok9yd",
      "web-oy12jpq8th",
      "web-njt1a659y3",
      "web-0moatrysma",
      "web-rol8lws1su",
      "web-5dcvyu2e3o",
      "web-pbygeqt23f",
      "web-2vopk0u3at",
      "web-z05ynepbb8",
      "web-w89ivzi3yy",
      "web-zsq4x8erw9",
      "web-e24f2jueat",
      "web-czjmkgjm39",
      "web-zmqk57h8de",
      "web-3lbmd3cfus",
      "web-rriy0cnzkj",
      "web-xwwu65hc28",
      "web-aaneedjxk2",
      "web-opvrqn6jj1",
      "web-vu4a22a7v2",
      "web-ef1tsxh9dj",
      "web-9hw9ymagbg",
      "web-3oxtq95q7r",
      "web-pr1zo1laqa",
      "web-mqs76nkev9",
      "web-ew2qioxrxr",
      "web-q2ftvustiz",
      "web-p5gg10npnj",
      "web-1cmt7u0u5s",
      "web-lybltaafxq",
      "web-466wnk1qw5",
      "web-l572a5tk9x",
      "web-8wf3a3bbfn",
      "web-tn5coyxrrp",
      "web-r8vreps1hr",
      "web-cjfomgqkkf",
      "web-hw0qa95laz",
      "web-qej7q1up53",
      "web-c6bp30mkms",
      "web-x1z237i4nt",
      "web-0d0vnx5z0b",
      "web-fuyvzcy440",
      "web-219lxaankc",
      "web-y0a272eikc",
      "web-geudwsn0ez",
      "web-g3uaz692el",
      "web-gdl177ef8b",
      "web-c3a9qu77qp",
      "web-mv47d5wfyt",
      "web-oeirn14b50",
      "web-xvsp1s8w36",
      "web-7dk91s6n1v",
      "web-z4sch25n1o",
      "web-2jv4w62232",
      "web-mdz00xweya",
      "web-2np2b1h23y",
      "web-n7bjsueji8",
      "web-vd691k2iq9",
      "web-o0j8y95gjp",
      "web-cimi51rgsx",
      "web-70ft9gx7rl",
      "web-dogpkm0g9g",
      "web-3wzs8fmsbk",
      "web-ge2t7isohx",
      "web-2d818oq144",
      "web-z2dzbcngn5",
      "web-ur7oalcmza",
      "web-y8ah296knj",
      "web-wrlgo56g52",
      "web-endpiclfh8",
      "web-zr0m5nfpkn",
      "web-q0fiwt6mra",
      "web-5qsn7e2bs3",
      "web-99hhrkdacc",
      "web-fqxb4k768e",
      "web-j8zslh10rb",
      "web-nxp9f27mjx",
      "web-k34mioaxfn",
      "web-6cv4ic99hu",
      "web-rdl8cl5z2d",
      "web-l501x0wfm8",
      "web-1q3ezry4p5",
      "web-wyynnr7ia5",
      "web-7ojvx09tzr",
      "web-kcup65qw4g",
      "web-qm2ie1zeyg",
      "web-zl5tewjtg6",
      "web-tjcalbd6s0",
      "web-flg5xx6z2i",
      "web-at1d2xgtw6",
      "web-yent1g2oto",
      "web-l0anljuurm",
      "web-g25v01xc1n",
      "web-3hyczugrqd",
      "web-k0cobh4p56",
      "web-o6joq8q67n",
      "web-v0f4w3icmr",
      "web-t3o05royx8",
      "web-2j5ndi99vf",
      "web-nojnhmjqky",
      "web-p2xl3cg2xv",
      "web-qst74m5225",
      "web-h3ukfusq6m",
      "web-vdny2frwo9",
      "web-kuynuand9z",
      "web-xdetu6skaa",
      "web-evg9ugzu2n",
      "web-t7q3vhm2pc",
      "web-64poyv0r8a",
      "web-n64lkycbaz",
      "web-sadkrpa5qg",
      "web-ukkj69y3tv",
      "web-lj5hteqtsm",
      "web-rweevg7dzr",
      "web-4xz63c8nn5",
      "web-kupc2hwtn6",
      "web-2olcrvx3jn",
      "web-1oseumrpjk",
      "web-y3gopmkd9q",
      "web-flwu5fmhi8",
      "web-41csskn3yh",
      "web-p244ts9pci",
      "web-450wd23uga",
      "web-wne63obt9o",
      "web-8guvy8bjh1",
      "web-juho80x0f5",
      "web-uinp6fl5iw",
      "web-x8gzaoqt5k",
      "web-xamvchqde7",
      "web-fum2p617vu",
      "web-3t3asdriwd",
      "web-6ep5jtcsrh",
      "web-2aiy0umzis",
      "web-3xgtin9jro",
      "web-mlquu5yy5i",
      "web-f52bdpynyp",
      "web-1j2pcdktep",
      "web-5wkrgu5x7a",
      "web-d0p0qng63m",
      "web-9gd6wf7rq8",
      "web-rwahq629rg",
      "web-xhcjvceto0",
      "web-54xgavjhiq",
      "web-a0swqbcdtw",
      "web-7sclug65fy",
      "web-m1uv1ytlfi",
      "web-xu72hh0muw",
      "web-juc4uoshxi",
      "web-7vmj8c2lvu",
      "web-amguo1esnk",
      "web-pyta76xpy6",
      "web-oxzb0bbfld",
      "web-auwoufu2po",
      "web-w60ubox4xr",
      "web-w0308muruj",
      "web-h1nwabwhxu",
      "web-52rzywgw07",
      "web-y4mwi20ejz",
      "web-z4o4jx1b85",
      "web-553c6xof9t",
      "web-d8bn4xwu2a",
      "web-745i4og0sy",
      "web-m28f5sj49j",
      "web-p53gfb98hl",
      "web-hunpfupxyn",
      "web-7tfdjzu3gp",
      "web-kske2f4k6h",
      "web-27q9h3uaua",
      "web-b1mmnx3k6g",
      "web-jwko08jd0h",
      "web-j5iw3ldnft",
      "web-8pqp36gtvq",
      "web-oevibag51m",
      "web-fddqn9mbme",
      "web-9wnu69xe4q",
      "web-hdghu16j7g",
      "web-e9cbh1nfqj",
      "web-nuzjxlet9j",
      "web-sgedmldh0d",
      "web-yfc9k9qdw1",
      "web-x9wkfm98a7",
      "web-fiix8ogwxe",
      "web-cavjpy8m4x",
      "web-edb8l2dazq",
      "web-4vg3b74ijr",
      "web-de1980x2km",
      "web-i1d7y602q4",
      "web-kvvil56dwf",
      "web-pecuxoyn1q",
      "web-uo60owwkzy",
      "web-d77x17mehz",
      "web-96fydhk4mg",
      "web-by5cqhe0t3",
      "web-4pqem4xjht",
      "web-yhr3jhnl0i",
      "web-vk23hzbef",
      "web-k8544zjgde",
      "web-o4x8dpo6ab",
      "web-63xhiehksa",
      "web-mmk8m8cfpv",
      "web-lg62zv0c7f",
      "web-cax61ynh4s",
      "web-2cpscskgo7",
      "web-f8rxjt0ypd",
      "web-5r41y5tctl",
      "web-03r27cgs7t",
      "web-q2k5a5vxb9",
      "web-k277wazzkh",
      "web-utdbsn3h60",
      "web-l0uhe83inb",
      "web-gfaeq9hdaa",
      "web-m6y41y5aw2",
      "web-ejz4x48t93",
      "web-0374i2ifsq",
      "web-x7t5m2180t",
      "web-ityaypnnou",
      "web-1sc9khnjdn",
      "web-9lx1iy03cg",
      "web-wcii07s3k5",
      "web-ze72xlvl3l",
      "web-slw3vhyc1l",
      "web-at1azsuf67",
      "web-ck6i485lyc",
      "web-gf52qtk65f",
      "web-2s6687rtwe",
      "web-v40qiy9xa1",
      "web-6grrpaeipu",
      "web-04hl6aov31",
      "web-0iwanhm0of",
      "web-0wm9ndnlon",
      "web-6a7eki06up",
      "web-6dxpw81jv9",
      "web-49adzst19w",
      "web-9qxrxj4uv2",
      "web-kon0v334l4",
      "web-bzh2i3k1vr",
      "web-ptf00526kz",
      "web-hiztryx5p9",
      "web-iofszqmolj",
      "web-m66otlogve",
      "web-yn9170fqjg",
      "web-yramcgfzql",
      "web-a8o60msbqy",
      "web-zq4w4pdh4i",
      "web-mt7sizq9jb",
      "web-sxjt0pp5wv",
      "web-mag9nvzipx",
      "web-nxyv3awhnw",
      "web-wnue9nd00w",
      "web-1fvxzzsd0j",
      "web-lxesgkolux",
      "web-d4j8gfmd1y",
      "web-7q1osxaq0p",
      "web-1mx05s9xza",
      "web-v9zi9n2erd",
      "web-nvpp7jwczm",
      "web-66ubpvwzv3",
      "web-tdp1pp7g1j",
      "web-hruyoreq9t",
      "web-cvnz0rdj51",
      "web-ti4eqjriau",
      "web-v0k4a4wff5",
      "web-jo7so3omb7",
      "web-fmphh5pqlz",
      "web-xl7luirtxi",
      "web-nu39b4udfg",
      "web-yd21w6uwmv",
      "web-0iep8kn11z",
      "web-9uh9ikpeyk",
      "web-cn9itu7y7p",
      "web-5klrareve3",
      "web-l2lhqeryxn",
      "web-rm9272g0pq",
      "web-v2i5el15me",
      "web-d0h5pme4n9",
      "web-s87jielwgj",
      "web-f3yymo94ii",
      "web-ezxdcj8j4",
      "web-r1mhuz4cei",
      "web-62lvwwvqqh",
      "web-iip2pjl61r",
      "web-godnjb6e3c",
      "web-o7goi2zjye",
      "web-mstywnjbtn",
      "web-yjcmridg39",
      "web-yb33i4rlei",
      "web-0y4wn5tc5r",
      "web-5n12xiez2d",
      "web-2rms108vgd",
      "web-7beobcika7",
      "web-xzbdzg9lfk",
      "web-es8n41tyjv",
      "web-zk1w2rxvna",
      "web-c04l2td8ag",
      "web-b40ttvnert",
      "web-vtvkkzvqt2",
      "web-fbsjnag805",
      "web-x8wq4alfgg",
      "web-ftz7xczzd8",
      "web-2nuejhwvdm",
      "web-xivioqvnhw",
      "web-ye5vzj3rc8",
      "web-j17gmyi8af",
      "web-f92okxjlbw",
      "web-bx437qeb8x",
      "web-7r85qprq3r",
      "web-jd1ozgvfqv",
      "web-kytzb0uxwn",
      "web-odrq1batov",
      "web-y8dsxw6sct",
      "web-2c5e5u20wj",
      "web-bh7jqvjvdh",
      "web-rhx3c5t4rq",
      "web-5bcyt19693",
      "web-ri0rwqkuov",
      "web-cebxmu0isa",
      "web-x2dkx4ei3f",
      "web-zw382yzv8e",
      "web-9gy7k34wel",
      "web-bshqms0qrn",
      "web-zv839zorqt",
      "web-ng7ubwvfcn",
      "web-m19rs0u1bp",
      "web-lpnrs21vr8",
      "web-g0ib9h1v59",
      "web-o8bqflbk1b",
      "web-q2zjuruwds",
      "web-q7thz851ft",
      "web-uvajt6qqt8",
      "web-uoztp5jc9g",
      "web-wgq52jauu8",
      "web-albabrli2b",
      "web-93cts7k0m8",
      "web-2ufh44sv5x",
      "web-i61r2g8bul",
      "web-g48ht94yp1",
      "web-xfnsv83sgo",
      "web-rue19x2run",
      "web-1bt0j0qma5",
      "web-uwpeep3jnh",
      "web-pa863mhico",
      "web-x3wkqb7xay",
      "web-kstg6z48fs",
      "web-fo77cq54we",
      "web-g0dka8sfn1",
      "web-dgjpq0y7vy",
      "web-mmk0ck2uer",
      "web-kpitdyg68e",
      "web-147rcpg3wb",
      "web-t5vp89yvez",
      "web-ieuiyecish",
      "web-2ymjrhd8sz",
      "web-wj084w6q3x",
      "web-3pqakerjnc",
      "web-fmnqr99804",
      "web-9tdkgy7zdp",
      "web-so6e1kqagr",
      "web-8fjczcvxmt",
      "web-p0jbx5dmtm",
      "web-vl979haemu",
      "web-uzbz8m2k4b",
      "web-10e2ld6uyb",
      "web-k82c45wn6i",
      "web-73cb1f9a9f",
      "web-8a3v9yj7lu",
      "web-buxrcl6elr",
      "web-dl684fc364",
      "web-cm6xq14boq",
      "web-hbyjr6vn6a",
      "web-ngzeso5dw7",
      "web-73z8oru0lb",
      "web-j99ruw9k6a",
      "web-24qyf3fepg",
      "web-ml5hn2zf3l",
      "web-jaqojjmdhc",
      "web-c0fsm33yb7",
      "web-vwbtivsggd",
      "web-alvd93v8or",
      "web-yusexliwsc",
      "web-e4li4knao1",
      "web-nozd4p9b5x",
      "web-p7bfpfqnzc",
      "web-pxmuqkai04",
      "web-paoat9r35k",
      "web-tz45cm0v1z",
      "web-2yqq5vvdkh",
      "web-1neij8s6ix",
      "web-fw2kjd7z5a",
      "web-ht2nrvmuai",
      "web-gfiqgrlmm4",
      "web-ldfodpr6o0",
      "web-rddglsacwj",
      "web-q7l7tafrgp",
      "web-7pwicst81k",
      "web-zvjyuh2xoh",
      "web-w17dcn3cs8",
      "web-ljeh1smwhq",
      "web-4zk6ndlu5b",
      "web-h96p0i0yzf",
      "web-61vwo8q4p3",
      "web-gxq23olcwr",
      "web-gxb566oo6x",
      "web-uauv89dvun",
      "web-c5ffs8glln",
      "web-4fpxca3u71",
      "web-vqx25tuj0f",
      "web-2vxsg3rc8l",
      "web-n56yxvnhre",
      "web-ptsmrcz14q",
      "web-3jx8qh3v3a",
      "web-f5dgdsnwuv",
      "web-t3jzai16ck",
      "web-ibma3t9qds",
      "web-5npr905whs",
      "web-ud49qwsre3",
      "web-am1edr87a6",
      "web-l2f4oy9oj9",
      "web-35u2ivjgnz",
      "web-schsfg5i35",
      "web-5wfi7lw0ib",
      "web-k9nc1omaku",
      "web-91j7fcqilo",
      "web-0ja378d0cn",
      "web-33b8mawcnz",
      "web-gnokyhfw2e",
      "web-93ki7hwcp6",
      "web-he2jul54wx",
      "web-3m431wycb2",
      "web-xxk4lyi9o1",
      "web-wcbkf2k6av",
      "web-rrp6vwms1w",
      "web-r29tatolk6",
      "web-4xzc4hiy36",
      "web-0106z1trjy",
      "web-qksn8mukdx",
      "web-xyzu4ikzn2",
      "web-2l1pgmi0ag",
      "web-fj5d7ejxcn",
      "web-jo3stzvw8o",
      "web-yddn3nl3ue",
      "web-62nwqizum5",
      "web-kghsgpeif0",
      "web-i93gpveuoi",
      "web-qp0tx0mnqj",
      "web-jt53x76ixb",
      "web-c3h8e78n6p",
      "web-u64r5bq1gx",
      "web-fdwzkif3d3",
      "web-il9jmgt5yu",
      "web-xkqvk7ejes",
      "web-b67y4stpzc",
      "web-5sgclky8k3",
      "web-0g74o4p5k2",
      "web-f7egmqqom1",
      "web-13v8b2nvpp",
      "web-tbst1tni6t",
      "web-zh37c7uyq0",
      "web-rr0we85bjs",
      "web-oa4zxl67ts",
      "web-2g0cxp1ofh",
      "web-1h3eci3i7j",
      "web-ztk58poea4",
      "web-ry5qsrco2b",
      "web-pt80myrii5",
      "web-mlncgxsqow",
      "web-4u3e0czvqv",
      "web-v6pkbl9ehg",
      "web-xttbu1u4zr",
      "web-rgatc9dvx2",
      "web-uwtuzest3s",
      "web-bsq2bfsy5",
      "web-tja80qxlzu",
      "web-jjqdro5iqb",
      "web-4507tdggwn",
      "web-6owcaou6oh",
      "web-ib7eveo2fy",
      "web-ky98wvfpx6",
      "web-xgyqd6iwda",
      "web-a5ljromapp",
      "web-6oo2nw5vxu",
      "web-7m05yq60gg",
      "web-cc8xqk6rtc",
      "web-vykuxejh03",
      "web-6i3olsm1qk",
      "web-ai2du2h3br",
      "web-zo500q9a07",
      "web-kkiv5o2m0o",
      "web-y4sqfuefjd",
      "web-ordpwc5y02",
      "web-i08lh1ua95",
      "web-9pvtwj9udo",
      "web-5368nykzbt",
      "web-hy7332uc3e",
      "web-b2iwvrf0q7",
      "web-2m6tnepbn3",
      "web-83hpwvzws8",
      "web-33fq56zk9o",
      "web-sexzz4nc58",
      "web-6l18kv3r74",
      "web-nztqhreeyp",
      "web-s0xcxtodw7",
      "web-4gnm8tr9kj",
      "web-8dohrkszsu",
      "web-irm031f5wd",
      "web-v0euaep7vi",
      "web-oa8kbdlna2",
      "web-fls8kfyxyl",
      "web-gz6778r5nk",
      "web-zkweq40dtc",
      "web-ovayfb5ydv",
      "web-cco880gfwr",
      "web-ln9nd1zwrd",
      "web-elu3656sz8",
      "web-s0zwb54sx2",
      "web-6j6arx61hu",
      "web-rf1c7z374p",
      "web-gc69l4v7f8",
      "web-9vt1pthi2r",
      "web-qr1pft9a22",
      "web-7l89d5jksk",
      "web-qfcvxmnzj2",
      "web-6d1gmt62ws",
      "web-i8cz13wuou",
      "web-cxlgfd9fqx",
      "web-oult1pexcv",
      "web-o214mdkf0s",
      "web-9nkfo9ylm2",
      "web-g9qjfzeed8",
      "web-z8zh1u56ts",
      "web-4scn1an982"
    ],
    "expireAt": 1776054765099,
    "createdAt": 1775881965099
  },
  "ATH-MPP3-J2IW": {
    "usesLeft": 0,
    "totalDevices": 2,
    "devices": [
      "web-r1mhuz4cei",
      "web-l158rdrk0y"
    ],
    "expireAt": 0,
    "createdAt": 1775953423650
  },
  "ATH-XWJ8-ADRC": {
    "usesLeft": 0,
    "totalDevices": 1,
    "devices": [
      "web-95z8jb7wom"
    ],
    "expireAt": 0,
    "createdAt": 1775957981812
  },
  "HUY-FRREAL2": {
    "usesLeft": 0,
    "totalDevices": 600,
    "devices": [
      "web-r1mhuz4cei",
      "web-40l3nwk9mj",
      "web-be03s0fcte",
      "web-9714k2slb8",
      "web-ids7w6w58i",
      "web-xcs0o0i46u",
      "web-4idmwx76mq",
      "web-3bcgw0nody",
      "web-vb17fqhc1y",
      "web-lybltaafxq",
      "web-oqwmvnyw5o",
      "web-bii68tf75f",
      "web-dq15qhfxb9",
      "web-lc7h1xntzz",
      "web-opbem37yjh",
      "web-g8tuhyfegs",
      "web-cjfomgqkkf",
      "web-y5rf15zi2",
      "web-54eqz3c9cd",
      "web-1no8lbg5n8",
      "web-sdemhl63s3",
      "web-webvvv6q1p",
      "web-8ln075atc6",
      "web-c5gpra67p0",
      "web-m4bphaolwj",
      "web-s7vhha1c5a",
      "web-7ym8ajn0w3",
      "web-5u3irwqn6h",
      "web-5580utub0e",
      "web-41csskn3yh",
      "web-r890b97wcq",
      "web-qt024f6tsi",
      "web-3fyk3oxhpx",
      "web-u9vnxyruua",
      "web-o1rif7wubz",
      "web-88zvoy1wvf",
      "web-ylb1nf8jqi",
      "web-kqk3w5gnts",
      "web-giecf8o3xd",
      "web-t3o05royx8",
      "web-9x788x5bum",
      "web-7ojvx09tzr",
      "web-e24f2jueat",
      "web-ubkig0w9ac",
      "web-jhv80o9lr2",
      "web-ycfktvv99o",
      "web-0q1ma7i8jq",
      "web-loy2aha04d",
      "web-f0mj8ino5u",
      "web-521py7ryg7",
      "web-3j088n19tb",
      "web-8xfsbyrc7s",
      "web-zw382yzv8e",
      "web-mjw6c0kvcm",
      "web-anx5e3gpcf",
      "web-qm9vaiczku",
      "web-k7ikl5olon",
      "web-p55bn8vfqq",
      "web-hmy1kkcx02",
      "web-mmn407xjcp",
      "web-nlm7gasqgz",
      "web-1atdrjkw06",
      "web-z4sch25n1o",
      "web-99etbr45de",
      "web-6elxafwzv2",
      "web-utdbsn3h60",
      "web-0g74o4p5k2",
      "web-iif7levrcu",
      "web-gnh7ope5si",
      "web-c04l2td8ag",
      "web-3m3nvqgbjn",
      "web-f8a4zuq2o8",
      "web-fj5d7ejxcn",
      "web-96axotgtsm",
      "web-71w4ktga75",
      "web-23ck8wpxrm",
      "web-swaabvimpk",
      "web-7nbftf5uxu",
      "web-gcfwprdvca",
      "web-dqkv8nwpy9",
      "web-b5szuigigk",
      "web-0k02odfoca",
      "web-l32r0f8d9q",
      "web-dkix2xfvtm",
      "web-6hoyxwrw44",
      "web-pr1zo1laqa",
      "web-fj51pi3t2l",
      "web-t9583goc3x",
      "web-5sgu74dmus",
      "web-ycdpslzjdw",
      "web-gb9tg835n7",
      "web-r29tr9wzm4",
      "web-l8zo4fz9e2",
      "web-7ynqgy5us1",
      "web-mlw0021zhe",
      "web-zgcrd48b5f",
      "web-r3gjv5j5jb",
      "web-ynbzjdkris",
      "web-rx2ifzftnp",
      "web-ystse5dm4f",
      "web-bk0nigu48k",
      "web-mn55pvw9u3",
      "web-lm9ip4o4a7",
      "web-pdvjzzi3go",
      "web-v6g8aztm7y",
      "web-f8bc9470td",
      "web-ubkboyxzph",
      "web-pqxeb4dtay",
      "web-dtfrzduplg",
      "web-whgvrjm3p9",
      "web-kzrqqrlfuu",
      "web-d77x17mehz",
      "web-2ejll6p21d",
      "web-w681lmjo58",
      "web-bhm3qmashj",
      "web-rq0aiw4j9p",
      "web-pv492lhf78",
      "web-8y898zmude",
      "web-bdspwurhyu",
      "web-fyr425b7ea",
      "web-moloz3pcft",
      "web-l0j8u6gkrj",
      "web-egtdu38pbk",
      "web-3hyczugrqd",
      "web-p86r5n6qvw",
      "web-zerthm3c57",
      "web-3ov9hhjpcu",
      "web-mu3byzv0m9",
      "web-5cpo7j6vjt",
      "web-229qwk9bzo",
      "web-3mp9cuwack",
      "web-da5nvdlf9d",
      "web-jei2mgodyt",
      "web-iz2r8gn1rl",
      "web-178qrpb67i",
      "web-54xgavjhiq",
      "web-w69ypagkug",
      "web-wk4w6jbp9j",
      "web-k9ziw9evr0",
      "web-w8o3uh54xm",
      "web-8vgxo1mjot",
      "web-ujf8nhr4fg",
      "web-4wyve6x0jq",
      "web-wuj9wmaopy",
      "web-xhee8btugt",
      "web-ridimsrg5m",
      "web-0iep8kn11z",
      "web-3v1dsydrq3",
      "web-1g15mdiqjx",
      "web-iiqvq1bjxq",
      "web-339mjdf40k",
      "web-9ih2ichb21",
      "web-f8811xzlh8",
      "web-to1u0vo8ge",
      "web-t98wtztzfc",
      "web-0anuejbh8c",
      "web-o2w3xw3hww",
      "web-p1getmssr1",
      "web-kcg0wweg0y",
      "web-fbj48njlx3",
      "web-x2wace9sbl",
      "web-uwpeep3jnh",
      "web-34k1qczf2i",
      "web-t4m0rt43u3",
      "web-bsq2bfsy5",
      "web-1lkym6yt8a",
      "web-ega66790is",
      "web-swkp6gjnn8",
      "web-127jt0f7gu",
      "web-gf1ojfsr03",
      "web-nym9a5nkty",
      "web-9c6v9horhr",
      "web-pzq93hpf9x",
      "web-u1h1g9b0lw",
      "web-vpzi8ifz1i",
      "web-qc1m8yr1cd",
      "web-h8oem7swpc",
      "web-xk3usd7w71",
      "web-67lsdnaew9",
      "web-l2zoovmtxa",
      "web-n6oolve5lf",
      "web-7w265m5n4j",
      "web-dsrlpeyzhb",
      "web-47x5x561go",
      "web-e5eotidpxo",
      "web-e78rl7sadw",
      "web-lh5ym01ye3",
      "web-3d0in0y0ov",
      "web-59ok5d6ew7",
      "web-6y7hu4fotp",
      "web-k7ir3s1mhf",
      "web-h6kn30ztw4",
      "web-vduwl0xww8",
      "web-mh1g8u0xk1",
      "web-v6f2mr1a8u",
      "web-ng7igvnyus",
      "web-3fclm9w5i9",
      "web-h01uabqg8h",
      "web-i4v8w4y8hw",
      "web-gi5plg7a3j",
      "web-41w8zw5xuj",
      "web-ucwisfx1bq",
      "web-38qn4ohx64",
      "web-t5vv1t1hnd",
      "web-849oo713rb",
      "web-g0ib9h1v59",
      "web-wcbkf2k6av",
      "web-n8awkilrqf",
      "web-t6t8bbez9k",
      "web-5svjoo4xpa",
      "web-xtqxqcuekq",
      "web-3c00zqngy2",
      "web-nvpp7jwczm",
      "web-zuvd4amt6t",
      "web-iwk3a9oqdl",
      "web-wcv7ve3syu",
      "web-npyj5v093p",
      "web-xwwu65hc28",
      "web-1h3eci3i7j",
      "web-ixgm990qg9",
      "web-2bwxbfc83f",
      "web-7z15r9cnjt",
      "web-jyeemwyjj8",
      "web-49i9enur06",
      "web-yfc9k9qdw1",
      "web-45cm5ifmfn",
      "web-slfoxep8x8",
      "web-sqclp8yte8",
      "web-4yjy1jtaxr",
      "web-j9d9nxb3lo",
      "web-sowsa0xc7k",
      "web-fkxb98kk0s",
      "web-ks867gcwof",
      "web-3p95s2x02f",
      "web-ziu2go3sg1",
      "web-x7nx29gwer",
      "web-0gefh5ildx",
      "web-787scg1021",
      "web-6d99zr1jq9",
      "web-wpsvpkdb6s",
      "web-4a92n8wsh8",
      "web-fwv3z6tibr",
      "web-ewyiuy2lgr",
      "web-zac8x4jhlw",
      "web-es1udb22ze",
      "web-l6zgjn4mbt",
      "web-un1zdrcuab",
      "web-n2t63tl6zj",
      "web-0d97fh9aik",
      "web-ej3neyl8pq",
      "web-bm626vpy9i",
      "web-eikl6g8gfh",
      "web-rzwzeupfqt",
      "web-yc5b00yk6g",
      "web-98bej0pvgh",
      "web-f2b0te8iol",
      "web-0ivcakb0f3",
      "web-fl7na2skc2",
      "web-ygweka1a39",
      "web-el0i8bmcya",
      "web-25gngoul8d",
      "web-a0h0xwxeeu",
      "web-ngdzk8lkbi",
      "web-ycj2rsimgl",
      "web-yp18yvmxvp",
      "web-30d0qfciv0",
      "web-2jv4w62232",
      "web-zdu5zbqoj2",
      "web-fjzh3t8cxl",
      "web-n99arfpiqw",
      "web-p9dx7krd7c",
      "web-1i5h2edizu",
      "web-qtwac040n8",
      "web-u50o62tbig",
      "web-ue12sz9njn",
      "web-vl8av6kqp9",
      "web-c5lmzy5mwz",
      "web-h96p0i0yzf",
      "web-ky1j8xq02d",
      "web-vw36s6osa2",
      "web-ya06f52kni",
      "web-ohm93x4uwv",
      "web-tx0jmgovo9",
      "web-0qj8mv3u7z",
      "web-6by1iq3ply",
      "web-nckz2f3z6e",
      "web-g1u13vvice",
      "web-d2dgw9qr74",
      "web-bdm1oedru6",
      "web-wpg99lpqcu",
      "web-xmmphwhufl",
      "web-5u9iqkrsn6",
      "web-q2jk4xzmm3",
      "web-6sbbzredvj",
      "web-7ub52tphbp",
      "web-8ijwcxvsx7",
      "web-pdsz48nco2",
      "web-mz583u3rbd",
      "web-53l39eevao",
      "web-l783agak4b",
      "web-5ab996ada2",
      "web-nw5gamces1",
      "web-z1ay7kgc01",
      "web-8f9f3hj1ry",
      "web-pxh3a0ohds",
      "web-78pynvgabx",
      "web-h58rldxqg1",
      "web-z95hmz0ef5",
      "web-k3ta6bwdcs",
      "web-9po5o9d9mo",
      "web-o19scmio3a",
      "web-ieuiyecish",
      "web-kixzpex7it",
      "web-q2p0bh7m9y",
      "web-235x15imnw",
      "web-l3utosfnfj",
      "web-ul9q4f06yj",
      "web-zzxdm8tcb6",
      "web-eaq06rcj9g",
      "web-k277wazzkh",
      "web-t8j2moi929",
      "web-3yrpoprwiq",
      "web-5ighkfaw05",
      "web-u2zqtr2st1",
      "web-a0swqbcdtw",
      "web-fqe5ehl93f",
      "web-6qe82nsig8",
      "web-baff48pzsf",
      "web-wypl9wecz",
      "web-arsoi61dba",
      "web-kc1nxaelqy",
      "web-t0fzfu06wn",
      "web-cf2ate5ihn",
      "web-6yhir97s7v",
      "web-ixmnqmofpp",
      "web-x38bneuq0h",
      "web-l1f3l32bms",
      "web-sadkrpa5qg",
      "web-mqerosc3hv",
      "web-fqjau1z2x6",
      "web-957470t40f",
      "web-3smq0clgwu",
      "web-ibma3t9qds",
      "web-g6siy83kgb",
      "web-tpq0sfsk2p",
      "web-rgth4zo716",
      "web-x4pmoloqjt",
      "web-jo7so3omb7",
      "web-vn9da428i8",
      "web-lbocjx690h",
      "web-gcvl7sbkke",
      "web-v5dhnt3jbg",
      "web-5ldoz01rt1",
      "web-2olcrvx3jn",
      "web-3sea14a10r",
      "web-25a89lyace",
      "web-ujrzponjbi",
      "web-9wnu69xe4q",
      "web-6oseo4mmvu",
      "web-ofexonbq8u",
      "web-2g0cxp1ofh",
      "web-ie5vdr7j08",
      "web-w2l81x1558",
      "web-alvyjtiyd4",
      "web-agqnig6k3x",
      "web-h6dk5xgsaj",
      "web-dascawvh7e",
      "web-1hedi81pz4",
      "web-b5dcnr4sgw",
      "web-ram0vhhm7k",
      "web-lfq8ztpkls",
      "web-g2fz05h7u6",
      "web-n5x2cs27vu",
      "web-w9xtxpg6co",
      "web-pargnmei1c",
      "web-9b60a9uwmp",
      "web-aeyet3ld4r",
      "web-egfe0jwevz",
      "web-fzfhgyol7o",
      "web-idkqg8qgpr",
      "web-ngvkpm3bba",
      "web-03r27cgs7t",
      "web-82c69f1k1h",
      "web-nfubiyu9jl",
      "web-ynkr8uhmid",
      "web-0p1o8k6jnq",
      "web-v4tbl3gyyw",
      "web-ypwojwyihs",
      "web-cpjc7zlrhx",
      "web-olakujnuel",
      "web-8kar6qetz6",
      "web-vtkqke1v6y",
      "web-rol8lws1su",
      "web-eb2kmnzd9w",
      "web-rhx3c5t4rq",
      "web-b3l7kgbgeq",
      "web-e9zbphh9qg",
      "web-bimjn8nsml",
      "web-utly78zqmz",
      "web-jzaa6o09l9",
      "web-w9ij2j65s7",
      "web-zniitxj6l5",
      "web-u1j7yyuuaa",
      "web-tdvfbxt52j",
      "web-cuyaskvkb7",
      "web-8k75ne0t3a",
      "web-p5vbhyhym8",
      "web-y0a272eikc",
      "web-y4d83f58l3",
      "web-6j6arx61hu",
      "web-9ilsgn4ebt",
      "web-m5l73xwval",
      "web-l572a5tk9x",
      "web-ac2mbx47ec",
      "web-4c8e2vjp99",
      "web-wp3dtfml0o",
      "web-wa829psq1b",
      "web-twc4yv72mz",
      "web-jk1atenq0m",
      "web-bxye5aijqs",
      "web-k9nc1omaku",
      "web-7xa4isadd8",
      "web-ee25dehejm",
      "web-y5yhpyb29d",
      "web-8ryxof4ahi",
      "web-cqm42vi7dt",
      "web-e30n17kgq1",
      "web-yx2u1nipis",
      "web-k0oiy47ocf",
      "web-wriix6hd7o",
      "web-2hd7e9kobz",
      "web-gv9dunr7nl",
      "web-9przklu7n4",
      "web-quurrtllet",
      "web-gisdyd4h61",
      "web-vc7zh2g1z5",
      "web-53f15gssws",
      "web-t9keb48uzk",
      "web-04cze2z129",
      "web-036zh3n983",
      "web-ktqe2u4afr",
      "web-x764eek84b",
      "web-6cv4ic99hu",
      "web-qa0zyrboqh",
      "web-lr1s2lrsq6",
      "web-0honkg03ku",
      "web-w3fru1jpks",
      "web-igca26vpby",
      "web-7ya5x8dvy4",
      "web-z9126zjq86",
      "web-zmbupllawd",
      "web-n1uhobujgk",
      "web-gr4mmpu72r",
      "web-q4fjg9oxss",
      "web-3cozbfr7w9",
      "web-gyt7tspu1e",
      "web-lvbm135azc",
      "web-alweef8m8q",
      "web-sx9eo8yeai",
      "web-vbf9q0hu8s",
      "web-iuhs77aj8u",
      "web-lgxvbrkutw",
      "web-46nxcfmvp5",
      "web-kgd9kso3i9",
      "web-28l9qxhktc",
      "web-l7gici1mzu",
      "web-lvflblr643",
      "web-u8vhmumvl3",
      "web-4dpx9giy8z",
      "web-4r3v76hhj2",
      "web-89w0q4zxgi",
      "web-5ha2i7absy",
      "web-vkoskoqyxc",
      "web-c3pdu5j8zn",
      "web-k2eccwxpbu",
      "web-vegm6qkn3s",
      "web-x6b512rzwp",
      "web-3hg2znbgxk",
      "web-xsfnjv9xas",
      "web-jrpctc9ovx",
      "web-5a7k2rrg4i",
      "web-cnuptu6ni3",
      "web-x3d4944myc",
      "web-jq05h07you",
      "web-9y3hk7umhq",
      "web-9tt52k48kw",
      "web-yuazs5h43j",
      "web-h9z76h21mu",
      "web-f3cpulicbz",
      "web-7g0k38eh5v",
      "web-ow6kqi64tp",
      "web-mp6x08yhhn",
      "web-metbrjqtqf",
      "web-kb8zjie9sn",
      "web-lpt0ihkul6",
      "web-vj5xqo7b1e",
      "web-ag85lbafq2",
      "web-id8vygdzr4",
      "web-pvvk6fj3x8",
      "web-wwkg3gctar",
      "web-lqjr6nea2w",
      "web-72p72pp196",
      "web-d27ax7o29d",
      "web-cxcl0f1woz",
      "web-4tn91np18v",
      "web-27mpgbrxsl",
      "web-3fvsn7jjib",
      "web-pmxhj6l3u3",
      "web-x8hiknpoez",
      "web-ju5d04qfcy",
      "web-qfcvxmnzj2",
      "web-sbk7c0ks2x",
      "web-i9xx07cqjv",
      "web-v6r29608bn",
      "web-3lxlwxgkn1",
      "web-skxpyywy1",
      "web-vbj1b0xx2o",
      "web-ktadrcpiuc",
      "web-70oabcn00m",
      "web-urgqteaulo",
      "web-qajvhi5yj7",
      "web-juovty2nrl",
      "web-f420yooaws",
      "web-8k6tp62qau",
      "web-wyqwxha3k7",
      "web-i6jyno75gn",
      "web-qdx2uyyrxd",
      "web-q7s3h6yi2y",
      "web-7cb8zqexpr",
      "web-e1cqdhzn9r",
      "web-04m3mzbfx4",
      "web-wb4ypkmaij",
      "web-p5p04i3qzp",
      "web-ygd0bhdqhy",
      "web-rf2ybt5den",
      "web-tpw4emixt3",
      "web-d53c4905dr",
      "web-v2c3zv5g8i",
      "web-hps3lvtehb",
      "web-v198u6nuap",
      "web-i1gev0aleq",
      "web-1a4b3d9bao",
      "web-rxo54omq2u",
      "web-oq2d4ukngm",
      "web-0mu0g23gkp",
      "web-7nlj0mo7q7",
      "web-nijnvuubn",
      "web-4ckxptu64t",
      "web-tufogk8jc5",
      "web-6hpzapszz9",
      "web-sa43a0a12m",
      "web-0mpsm1otsc",
      "web-z0p23ejyiu",
      "web-ophyj3kv59",
      "web-1uik0mh33n",
      "web-ibhkfpkwdh",
      "web-w1sy2keic7",
      "web-90q7dik4uj",
      "web-s2txvh9zsq",
      "web-5sh6agq3nl",
      "web-kz3cqw1iah",
      "web-pw9i1cljtc",
      "web-6ttyjt6ccd",
      "web-qibkitg22s",
      "web-idumszg7zf",
      "web-fvgjn4dr59",
      "web-gg9s1fbxui",
      "web-thohzof7c5",
      "web-2jx6swdlza",
      "web-a7zivuukej",
      "web-aqj7btz1zg",
      "web-24sjo70mnv",
      "web-rbz6uix4p7",
      "web-03d4x6t7k2",
      "web-lyotsnzpsg",
      "web-k9bzd8z1z1",
      "web-r7lz3iqo5a",
      "web-h2kb534frr",
      "web-uj8v7dg8qx",
      "web-acqskvdddg",
      "web-jnawl6k4l3",
      "web-4sopo73j0t",
      "web-0ed409psfj",
      "web-484y8yur0w",
      "web-0bsubhptmu",
      "web-snm0fg9klx",
      "web-lc1wvdwnau",
      "web-10e2ld6uyb",
      "web-3ke7032m86",
      "web-kae86b8f62",
      "web-f170oawinr",
      "web-no5n1s6ooj",
      "web-0968bqhobv",
      "web-txbh5ieor",
      "web-24n5wk5p6d",
      "web-wi438iofzr",
      "web-2kgavhjyu4",
      "web-wf0ryus8xq",
      "web-2lwkr98rvv",
      "web-z499xps3pv"
    ],
    "expireAt": 1776140243341,
    "createdAt": 1775967443342
  },
  "ATH-09O5-SSIQ": {
    "usesLeft": 0,
    "totalDevices": 1,
    "devices": [
      "web-i2ki0msss3"
    ],
    "expireAt": 0,
    "createdAt": 1775995575444
  },
  "ATH-YTWD-EOSS": {
    "usesLeft": 0,
    "totalDevices": 1,
    "devices": [
      "web-r1mhuz4cei"
    ],
    "expireAt": 1778598562549,
    "createdAt": 1776006562549
  },
  "ATH-BV6B-EC2L": {
    "usesLeft": 0,
    "totalDevices": 1,
    "devices": [
      "web-9rnpq12cwg"
    ],
    "expireAt": 0,
    "createdAt": 1776040586734
  },
  "ATH-9LHN-J4XJ": {
    "usesLeft": 0,
    "totalDevices": 1,
    "devices": [
      "web-7dsoednnqw"
    ],
    "expireAt": 0,
    "createdAt": 1776047857968
  },
  "HUY-FTTIKTOK3": {
    "usesLeft": 599,
    "totalDevices": 600,
    "devices": [
      "web-vkkk0fqqy6"
    ],
    "expireAt": 1776226973883,
    "createdAt": 1776054173883
  }
}